TIStan/__init__.py
TIStan/tests/__init__.py
TIStan/tests/sinusoid_data_20161004.dill
TIStan/tests/sinusoids.stan
TIStan/tests/tests.py
TIStan-0.1.3.dist-info/COPYING.LESSER
TIStan-0.1.3.dist-info/LICENSE
TIStan-0.1.3.dist-info/METADATA
TIStan-0.1.3.dist-info/WHEEL
TIStan-0.1.3.dist-info/top_level.txt
TIStan-0.1.3.dist-info/RECORD
