Metadata-Version: 2.1
Name: TIStan
Version: 0.1.3
Summary: Adaptively annealed thermodynamic integration with Stan
Home-page: https://github.com/rwhender/ti-stan
Author: Wesley Henderson
Author-email: wesley.henderson11@gmail.com
License: LGPL-3.0-or-later
Platform: UNKNOWN
Requires-Dist: pystan
Requires-Dist: numpy
Requires-Dist: matplotlib
Requires-Dist: dill
